{
    "name": "Andhika Surya Syahputra- Electronic Engineering Technology Student",
    "description": "I am an Electrical Engineering student with a strong interest in electronics, programming, and control systems. I have hands-on experience through internships at PPTIK ITB and Gumaya Tower Hotel, where I developed practical skills in PCB prototyping, soldering, troubleshooting, and programming using C++ and Python. I am a fast learner, capable of working independently or in a team, and committed to contributing to innovative and efficient technological solutions.",
    "profileImage": "images/pas.jpg",
    "email": "dhika13bugaji@gmail.com",
    "phone": "+62 (888) 0247-1338",
    "socialMedia": [
        {
            "platform": "LinkedIn",
            "url": "https://www.linkedin.com/in/andhikasurya1301"
        },
        {
            "platform": "GitHub",
            "url": "https://github.com/13dhika"
        },
        {
            "platform": "Instagram",
            "url": "https://instagram.com/a.surya.sp"
        }
    ],
    "cv": {
			"text": "Download CV",
			"file": "docs/andhika-cv.pdf",
			"icon": "fas fa-file-pdf"
	},
    "skills": [
        {"name": "Electrical Wiring and Installation ", "icon": "fas fa-heart-pulse", "level": 90},
        {"name": "PLC Programming", "icon": "fas fa-microchip", "level": 70},
        {"name": "Internet of Things", "icon": "fas fa-wifi", "level": 90},
        {"name": "Hardware Design", "icon": "fas fa-desktop", "level": 90},
	{"name": "Hardware Programming", "icon": "fas fa-c", "level": 90},
        {"name": "Web Programming", "icon": "fab fa-js", "level": 80},
	{"name": "Digital Office Tools", "icon": "fas fa-list-check", "level": 95},
	{"name": "Foreign Languages", "icon": "fas fa-language", "level": 85}
    ]
}
